kstreams/__init__.py
kstreams/backends/__init__.py
kstreams/backends/kafka.py
kstreams/batch.py
kstreams/clients.py
kstreams/consts.py
kstreams/create.py
kstreams/engine.py
kstreams/exceptions.py
kstreams/middleware/__init__.py
kstreams/middleware/middleware.py
kstreams/middleware/udf_middleware.py
kstreams/prometheus/__init__.py
kstreams/prometheus/monitor.py
kstreams/py.typed
kstreams/rebalance_listener.py
kstreams/serializers.py
kstreams/streams.py
kstreams/streams_utils.py
kstreams/structs.py
kstreams/test_utils/__init__.py
kstreams/test_utils/structs.py
kstreams/test_utils/test_clients.py
kstreams/test_utils/test_utils.py
kstreams/test_utils/topics.py
kstreams/types.py
kstreams/utils.py
kstreams-0.30.1.dist-info/METADATA
kstreams-0.30.1.dist-info/WHEEL
kstreams-0.30.1.dist-info/licenses/LICENSE
kstreams-0.30.1.dist-info/RECORD
