Metadata-Version: 2.4
Name: kstreams
Version: 0.30.1
Summary: Build simple kafka streams applications
License: Apache-2.0
License-File: LICENSE
Keywords: stream,processing,kafka,event streaming
Author: Marcos Schroh
Author-email: marcos.schroh@kpn.com
Maintainer: Santiago Fraire Willemoës
Maintainer-email: santiago.fraire@kpn.com
Requires-Python: >=3.10,<4.0
Classifier: Framework :: AsyncIO
Classifier: Intended Audience :: Developers
Classifier: License :: OSI Approved :: Apache Software License
Classifier: Programming Language :: Python :: 3
Classifier: Programming Language :: Python :: 3.10
Classifier: Programming Language :: Python :: 3.11
Classifier: Programming Language :: Python :: 3.12
Classifier: Programming Language :: Python :: 3.13
Classifier: Programming Language :: Python :: 3.14
Classifier: Programming Language :: Python :: Implementation :: CPython
Classifier: Topic :: Software Development :: Libraries :: Application Frameworks
Classifier: Topic :: System :: Distributed Computing
Classifier: Topic :: System :: Networking
Requires-Dist: PyYAML (>=5.4,<7.0.0)
Requires-Dist: aiokafka (<1.0)
Requires-Dist: future (>=1.0.0,<2.0.0)
Requires-Dist: prometheus-client (<1.0)
Requires-Dist: pydantic (>=2.0.0,<3.0.0)
